README.md
renderdown.py
setup.cfg
setup.py
renderdown.egg-info/PKG-INFO
renderdown.egg-info/SOURCES.txt
renderdown.egg-info/dependency_links.txt
renderdown.egg-info/entry_points.txt
renderdown.egg-info/requires.txt
renderdown.egg-info/top_level.txt