Metadata-Version: 2.1
Name: renderdown
Version: 0.2.0
Summary: Generate Markdown text from templates.
Home-page: https://github.com/jeffhung/RenderDown
Author: Jeff Hung
Author-email: jeff.cc.hung@gmail.com
License: MIT
Platform: UNKNOWN
Classifier: Environment :: Console
Classifier: Intended Audience :: Developers
Classifier: License :: OSI Approved :: MIT License
Classifier: Topic :: Utilities
